dival/__init__.py
dival/config.py
dival/data.py
dival/evaluation.py
dival/hyper_param_search.py
dival/measure.py
dival/reference_reconstructors.py
dival/version.py
dival/datasets/__init__.py
dival/datasets/angle_subset_dataset.py
dival/datasets/cached_dataset.py
dival/datasets/dataset.py
dival/datasets/ellipses_dataset.py
dival/datasets/fbp_dataset.py
dival/datasets/lodopab_dataset.py
dival/datasets/reordered_dataset.py
dival/datasets/standard.py
dival/reconstructors/__init__.py
dival/reconstructors/dip_ct_reconstructor.py
dival/reconstructors/fbpunet_reconstructor.py
dival/reconstructors/iradonmap_reconstructor.py
dival/reconstructors/learnedgd_reconstructor.py
dival/reconstructors/learnedpd_reconstructor.py
dival/reconstructors/odl_reconstructors.py
dival/reconstructors/reconstructor.py
dival/reconstructors/regression_reconstructors.py
dival/reconstructors/standard_learned_reconstructor.py
dival/reconstructors/tvadam_ct_reconstructor.py
dival/reconstructors/networks/__init__.py
dival/reconstructors/networks/iradonmap.py
dival/reconstructors/networks/iterative.py
dival/reconstructors/networks/unet.py
dival/util/__init__.py
dival/util/constants.py
dival/util/download.py
dival/util/input.py
dival/util/odl_noise_random_state.py
dival/util/odl_utility.py
dival/util/plot.py
dival/util/std_out_err_redirect_tqdm.py
dival/util/torch_losses.py
dival/util/torch_utility.py
dival/util/zenodo_download.py
dival-0.6.1.dist-info/AUTHORS.md
dival-0.6.1.dist-info/LICENSE
dival-0.6.1.dist-info/METADATA
dival-0.6.1.dist-info/WHEEL
dival-0.6.1.dist-info/top_level.txt
dival-0.6.1.dist-info/RECORD
